imapbackup/__init__.py
imapbackup/base.py
imapbackup/cli.py
imapbackup/mailbox.py
imapbackup-0.1.2.dist-info/LICENSE
imapbackup-0.1.2.dist-info/METADATA
imapbackup-0.1.2.dist-info/WHEEL
imapbackup-0.1.2.dist-info/entry_points.txt
imapbackup-0.1.2.dist-info/top_level.txt
imapbackup-0.1.2.dist-info/RECORD
