Metadata-Version: 2.1
Name: imapbackup
Version: 0.1.2
Summary: Download all emails from an IMAP server and save these emails to .eml files, and allow you to restore these emails to a new imap server.
Home-page: UNKNOWN
Author: zencore
Author-email: dobetter@zencore.cn
License: MIT
Keywords: imapbackup
Platform: UNKNOWN
Classifier: Development Status :: 5 - Production/Stable
Classifier: Intended Audience :: Developers
Classifier: Topic :: Software Development :: Libraries :: Python Modules
Classifier: License :: OSI Approved :: MIT License
Classifier: Programming Language :: Python :: 3
Classifier: Programming Language :: Python :: 3 :: Only
License-File: LICENSE
Requires-Dist: imapclient
Requires-Dist: imap-tools
Requires-Dist: click
Requires-Dist: zenutils (>=0.3.5)
Requires-Dist: python-dateutil
Requires-Dist: tabulate
